left_pad.py
setup.py
left_pad.egg-info/PKG-INFO
left_pad.egg-info/SOURCES.txt
left_pad.egg-info/dependency_links.txt
left_pad.egg-info/top_level.txt