Metadata-Version: 1.0
Name: left-pad
Version: 0.0.3
Summary: Pad a string to the left with any number of characters
Home-page: https://docs.python.org/2/library/stdtypes.html#str.rjust
Author: Matthew Perry
Author-email: perrygeo@gmail.com
License: BSD
Platform: UNKNOWN
